{"realms":[{"type":"pvp","population":"n/a","queue":false,"status":true,"name":"가로나","slug":"가로나","battlegroup":"격노의 전장","locale":"ko_KR","timezone":"Asia/Seoul","connected_realms":["가로나","줄진","굴단"]},{"type":"pvp","population":"n/a","queue":false,"status":true,"name":"굴단","slug":"굴단","battlegroup":"징벌의 전장","locale":"ko_KR","timezone":"Asia/Seoul","connected_realms":["가로나","줄진","굴단"]},{"type":"pvp","population":"low","queue":false,"status":true,"name":"노르간논","slug":"노르간논","battlegroup":"징벌의 전장","locale":"ko_KR","timezone":"Asia/Seoul","connected_realms":["달라란","말퓨리온","세나리우스","노르간논"]},{"type":"pvp","population":"low","queue":false,"status":true,"name":"달라란","slug":"달라란","battlegroup":"격노의 전장","locale":"ko_KR","timezone":"Asia/Seoul","connected_realms":["달라란","말퓨리온","세나리우스","노르간논"]},{"type":"pvp","population":"low","queue":false,"status":true,"name":"데스윙","slug":"데스윙","battlegroup":"격노의 전장","locale":"ko_KR","timezone":"Asia/Seoul","connected_realms":["알렉스트라자","데스윙"]},{"type":"pvp","population":"low","queue":false,"status":true,"name":"듀로탄","slug":"듀로탄","battlegroup":"징벌의 전장","locale":"ko_KR","timezone":"Asia/Seoul","connected_realms":["듀로탄"]},{"type":"pve","population":"low","queue":false,"status":true,"name":"렉사르","slug":"렉사르","battlegroup":"격노의 전장","locale":"ko_KR","timezone":"Asia/Seoul","connected_realms":["와일드해머","렉사르","윈드러너"]},{"type":"pvp","population":"low","queue":false,"status":true,"name":"말퓨리온","slug":"말퓨리온","battlegroup":"격노의 전장","locale":"ko_KR","timezone":"Asia/Seoul","connected_realms":["달라란","말퓨리온","세나리우스","노르간논"]},{"type":"pve","population":"low","queue":false,"status":true,"name":"불타는 군단","slug":"불타는-군단","battlegroup":"격노의 전장","locale":"ko_KR","timezone":"Asia/Seoul","connected_realms":["불타는-군단","스톰레이지"]},{"type":"pvp","population":"low","queue":false,"status":true,"name":"세나리우스","slug":"세나리우스","battlegroup":"격노의 전장","locale":"ko_KR","timezone":"Asia/Seoul","connected_realms":["달라란","말퓨리온","세나리우스","노르간논"]},{"type":"pve","population":"low","queue":false,"status":true,"name":"스톰레이지","slug":"스톰레이지","battlegroup":"징벌의 전장","locale":"ko_KR","timezone":"Asia/Seoul","connected_realms":["불타는-군단","스톰레이지"]},{"type":"pvp","population":"high","queue":false,"status":true,"name":"아즈샤라","slug":"아즈샤라","battlegroup":"징벌의 전장","locale":"ko_KR","timezone":"Asia/Seoul","connected_realms":["아즈샤라"]},{"type":"pvp","population":"low","queue":false,"status":true,"name":"알렉스트라자","slug":"알렉스트라자","battlegroup":"격노의 전장","locale":"ko_KR","timezone":"Asia/Seoul","connected_realms":["알렉스트라자","데스윙"]},{"type":"pve","population":"low","queue":false,"status":true,"name":"와일드해머","slug":"와일드해머","battlegroup":"격노의 전장","locale":"ko_KR","timezone":"Asia/Seoul","connected_realms":["와일드해머","렉사르","윈드러너"]},{"type":"pve","population":"low","queue":false,"status":true,"name":"윈드러너","slug":"윈드러너","battlegroup":"징벌의 전장","locale":"ko_KR","timezone":"Asia/Seoul","connected_realms":["와일드해머","렉사르","윈드러너"]},{"type":"pvp","population":"n/a","queue":false,"status":true,"name":"줄진","slug":"줄진","battlegroup":"징벌의 전장","locale":"ko_KR","timezone":"Asia/Seoul","connected_realms":["가로나","줄진","굴단"]},{"type":"pvp","population":"low","queue":false,"status":true,"name":"하이잘","slug":"하이잘","battlegroup":"격노의 전장","locale":"ko_KR","timezone":"Asia/Seoul","connected_realms":["하이잘"]},{"type":"pvp","population":"low","queue":false,"status":true,"name":"헬스크림","slug":"헬스크림","battlegroup":"격노의 전장","locale":"ko_KR","timezone":"Asia/Seoul","connected_realms":["헬스크림"]}]}